troubleshooting_mcp_server/__init__.py
troubleshooting_mcp_server/server.py
troubleshooting_mcp_server-1.0.1.dist-info/licenses/LICENSE
troubleshooting_mcp_server-1.0.1.dist-info/METADATA
troubleshooting_mcp_server-1.0.1.dist-info/WHEEL
troubleshooting_mcp_server-1.0.1.dist-info/entry_points.txt
troubleshooting_mcp_server-1.0.1.dist-info/top_level.txt
troubleshooting_mcp_server-1.0.1.dist-info/RECORD
