Metadata-Version: 2.4
Name: troubleshooting-mcp-server
Version: 1.0.1
Summary: A Model Context Protocol server for system troubleshooting and diagnostics
Home-page: https://github.com/yourusername/troubleshooting-mcp-server
Author: Your Name
Author-email: Samuel Amoh Ntim <amohntim123@gmail.com>
License: MIT
Project-URL: Homepage, https://github.com/Amoh-Ntim/troubleshooting-mcp-server
Project-URL: Repository, https://github.com/Amoh-Ntim/troubleshooting-mcp-server
Project-URL: Issues, https://github.com/Amoh-Ntim/troubleshooting-mcp-server/issues
Classifier: Development Status :: 4 - Beta
Classifier: Intended Audience :: Developers
Classifier: License :: OSI Approved :: MIT License
Classifier: Programming Language :: Python :: 3
Classifier: Programming Language :: Python :: 3.8
Classifier: Programming Language :: Python :: 3.9
Classifier: Programming Language :: Python :: 3.10
Classifier: Programming Language :: Python :: 3.11
Classifier: Programming Language :: Python :: 3.12
Requires-Python: >=3.8
License-File: LICENSE
Requires-Dist: mcp>=1.0.0
Dynamic: author
Dynamic: home-page
Dynamic: license-file
Dynamic: requires-python
